construction_requirements_integrator/__init__.py
construction_requirements_integrator/construction_requirements_integrator.py
construction_requirements_integrator-0.3.7.dist-info/LICENSE
construction_requirements_integrator-0.3.7.dist-info/METADATA
construction_requirements_integrator-0.3.7.dist-info/WHEEL
construction_requirements_integrator-0.3.7.dist-info/top_level.txt
construction_requirements_integrator-0.3.7.dist-info/RECORD
