Metadata-Version: 2.1
Name: construction-requirements-integrator
Version: 0.3.7
Summary: With the help of this module, classes can be inherited that are built and configured after their needs are met (instead of being launched immediately after creation).
Home-page: https://github.com/BehzadShayegh/construction-requirements-integrator
Author: Behzad Shayegh
Author-email: behzad.shayegh@ut.ac.ir
License: UNKNOWN
Project-URL: Bug Tracker, https://github.com/BehzadShayegh/construction-requirements-integrator/issues
Platform: UNKNOWN
Classifier: Programming Language :: Python :: 3
Classifier: License :: OSI Approved :: MIT License
Classifier: Operating System :: OS Independent
Requires-Python: >=3.6
License-File: LICENSE
